LICENSE
MANIFEST.in
README.rst
requirements.txt
setup.py
django_dynamodb_sessions.egg-info/PKG-INFO
django_dynamodb_sessions.egg-info/SOURCES.txt
django_dynamodb_sessions.egg-info/dependency_links.txt
django_dynamodb_sessions.egg-info/requires.txt
django_dynamodb_sessions.egg-info/top_level.txt
dynamodb_sessions/__init__.py
dynamodb_sessions/models.py
dynamodb_sessions/tests.py
dynamodb_sessions/backends/__init__.py
dynamodb_sessions/backends/cached_dynamodb.py
dynamodb_sessions/backends/dynamodb.py